boldqc/__init__.py
boldqc/__version__.py
boldqc/bids/__init__.py
boldqc/cli/__init__.py
boldqc/cli/get.py
boldqc/cli/process.py
boldqc/cli/tandem.py
boldqc/libexec/helpers.sh
boldqc/libexec/niftiqa.py
boldqc/libexec/niftiqa_wrapper.py
boldqc/libexec/stackcheck_ext.sh
boldqc/parsers/__init__.py
boldqc/state/__init__.py
boldqc/tasks/__init__.py
boldqc/tasks/niftiqa_wrapper.py
boldqc/tasks/stackcheck_ext.py
boldqc/xnat/__init__.py
boldqc_bu-0.0.1.data/scripts/boldQC.py
boldqc_bu-0.0.1.dist-info/licenses/LICENSE
boldqc_bu-0.0.1.dist-info/METADATA
boldqc_bu-0.0.1.dist-info/WHEEL
boldqc_bu-0.0.1.dist-info/top_level.txt
boldqc_bu-0.0.1.dist-info/RECORD
